{"code":"52395","name":"POINSON-LES-GRANCEY","department":"52","departmentName":"Haute-Marne","distributor":"MAIRIE DE POINSON-LES-GRANCEY","network":"POINSON-LES-GRANCEY","lastSampleDate":"2026-02-23T11:41:00Z","conclusion":"Eau d'alimentation conforme aux limites de qualité par dérogation et conforme aux références de qualité.","compliantOverall":false,"samplesCount":10,"paramsCount":52,"params":{"ECOLI":{"code":"ECOLI","label":"Escherichia coli /100ml - MF","value":0,"unit":"n/(100mL)","reference":null,"limit":"<=0 n/(100mL)","compliant_pc":false,"compliant_bact":true,"date":"2026-01-27T12:41:00Z"},"CL2LIB":{"code":"CL2LIB","label":"Chlore libre","value":0.11,"unit":"mg(Cl2)/L","reference":null,"limit":null,"compliant_pc":false,"compliant_bact":true,"date":"2026-01-27T12:41:00Z"},"NO3":{"code":"NO3","label":"Nitrates (en NO3)","value":37,"unit":"mg/L","reference":null,"limit":"<=50 mg/L","compliant_pc":false,"compliant_bact":true,"date":"2026-01-27T12:41:00Z"},"PH":{"code":"PH","label":"pH","value":7.8,"unit":"unité pH","reference":">=6,5 et <=9 unité pH","limit":null,"compliant_pc":false,"compliant_bact":true,"date":"2026-01-27T12:41:00Z"},"STRF":{"code":"STRF","label":"Entérocoques /100ml-MS","value":0,"unit":"n/(100mL)","reference":null,"limit":"<=0 n/(100mL)","compliant_pc":false,"compliant_bact":true,"date":"2026-01-27T12:41:00Z"},"CDT25":{"code":"CDT25","label":"Conductivité à 25°C","value":420,"unit":"µS/cm","reference":">=200 et <=1100 µS/cm","limit":null,"compliant_pc":false,"compliant_bact":true,"date":"2026-01-27T12:41:00Z"},"NO2":{"code":"NO2","label":"Nitrites (en NO2)","value":0,"unit":"mg/L","reference":null,"limit":"<=0,5 mg/L","compliant_pc":false,"compliant_bact":true,"date":"2026-01-27T12:41:00Z"},"NH4":{"code":"NH4","label":"Ammonium (en NH4)","value":0,"unit":"mg/L","reference":"<=0,1 mg/L","limit":null,"compliant_pc":false,"compliant_bact":true,"date":"2026-01-27T12:41:00Z"},"TH":{"code":"TH","label":"Titre hydrotimétrique","value":21,"unit":"°f","reference":null,"limit":null,"compliant_pc":false,"compliant_bact":true,"date":"2026-01-27T12:41:00Z"},"CL2TOT":{"code":"CL2TOT","label":"Chlore total","value":0.16,"unit":"mg(Cl2)/L","reference":null,"limit":null,"compliant_pc":false,"compliant_bact":true,"date":"2026-01-27T12:41:00Z"},"TURBNFU":{"code":"TURBNFU","label":"Turbidité néphélométrique NFU","value":0.2,"unit":"NFU","reference":"<=2 NFU","limit":null,"compliant_pc":false,"compliant_bact":true,"date":"2026-01-27T12:41:00Z"},"CTF":{"code":"CTF","label":"Bactéries coliformes /100ml-MS","value":0,"unit":"n/(100mL)","reference":"<=0 n/(100mL)","limit":null,"compliant_pc":false,"compliant_bact":true,"date":"2026-01-27T12:41:00Z"},"PFHXS":{"code":"PFHXS","label":"Perfluorohexane sulfonate (PFHXS)","value":0,"unit":"µg/L","reference":null,"limit":null,"compliant_pc":false,"compliant_bact":false,"date":"2025-08-12T14:24:00Z"},"PFDA":{"code":"PFDA","label":"Acide perfluoro-decanoïque (PFDA)","value":0,"unit":"µg/L","reference":null,"limit":null,"compliant_pc":false,"compliant_bact":false,"date":"2025-08-12T14:24:00Z"},"PFDS":{"code":"PFDS","label":"Acide perfluorodecane sulfonique (PFDS)","value":0,"unit":"µg/L","reference":null,"limit":null,"compliant_pc":false,"compliant_bact":false,"date":"2025-08-12T14:24:00Z"},"PFUNA":{"code":"PFUNA","label":"Acide perfluoro undecanoïque (PFUnA)","value":0,"unit":"µg/L","reference":null,"limit":null,"compliant_pc":false,"compliant_bact":false,"date":"2025-08-12T14:24:00Z"},"PFBS":{"code":"PFBS","label":"Acide sulfonique de perfluorobutane (PFBS)","value":0,"unit":"µg/L","reference":null,"limit":null,"compliant_pc":false,"compliant_bact":false,"date":"2025-08-12T14:24:00Z"},"PFUNDS":{"code":"PFUNDS","label":"Acide perfluoro undecane sulfonique (PFUnDS)","value":0,"unit":"µg/L","reference":null,"limit":null,"compliant_pc":false,"compliant_bact":false,"date":"2025-08-12T14:24:00Z"},"PFTRDA":{"code":"PFTRDA","label":"Acide perfluoro tridecanoique (PFTrDA)","value":0,"unit":"µg/L","reference":null,"limit":null,"compliant_pc":false,"compliant_bact":false,"date":"2025-08-12T14:24:00Z"},"PFOS":{"code":"PFOS","label":"Acide sulfonique de perfluorooctane (PFOS)","value":0,"unit":"µg/L","reference":null,"limit":null,"compliant_pc":false,"compliant_bact":false,"date":"2025-08-12T14:24:00Z"},"PFPEA":{"code":"PFPEA","label":"Acide perfluoropentanoïque (PFPEA)","value":0,"unit":"µg/L","reference":null,"limit":null,"compliant_pc":false,"compliant_bact":false,"date":"2025-08-12T14:24:00Z"},"PFNA":{"code":"PFNA","label":"Acide perfluoro-nonanoïque (PFNA)","value":0,"unit":"µg/L","reference":null,"limit":null,"compliant_pc":false,"compliant_bact":false,"date":"2025-08-12T14:24:00Z"},"PFHPS":{"code":"PFHPS","label":"Acide perfluoroheptane sulfonique (PFHpS)","value":0,"unit":"µg/L","reference":null,"limit":null,"compliant_pc":false,"compliant_bact":false,"date":"2025-08-12T14:24:00Z"},"PFPS":{"code":"PFPS","label":"Acide perfluoropentane sulfonique (PFPS)","value":0,"unit":"µg/L","reference":null,"limit":null,"compliant_pc":false,"compliant_bact":false,"date":"2025-08-12T14:24:00Z"},"SPFAS":{"code":"SPFAS","label":"Somme de 20 substances perfluoroalkylées (PFAS)","value":0,"unit":"µg/L","reference":null,"limit":"<=0,1 µg/L","compliant_pc":false,"compliant_bact":false,"date":"2025-08-12T14:24:00Z"},"PFBA":{"code":"PFBA","label":"Acide perfluorobutanoïque (PFBA)","value":0,"unit":"µg/L","reference":null,"limit":null,"compliant_pc":false,"compliant_bact":false,"date":"2025-08-12T14:24:00Z"},"PFDODA":{"code":"PFDODA","label":"Acide perfluorododécanoique (PFDoDA)","value":0,"unit":"µg/L","reference":null,"limit":null,"compliant_pc":false,"compliant_bact":false,"date":"2025-08-12T14:24:00Z"},"PFOA":{"code":"PFOA","label":"Acide perfluoro-octanoïque (PFOA)","value":0,"unit":"µg/L","reference":null,"limit":null,"compliant_pc":false,"compliant_bact":false,"date":"2025-08-12T14:24:00Z"},"PFTRDS":{"code":"PFTRDS","label":"Acide perfluoro tridecane sulfonique (PFTrDS)","value":0,"unit":"µg/L","reference":null,"limit":null,"compliant_pc":false,"compliant_bact":false,"date":"2025-08-12T14:24:00Z"},"PFHXA":{"code":"PFHXA","label":"Acide perfluorohexanoïque (PFHXA)","value":0,"unit":"µg/L","reference":null,"limit":null,"compliant_pc":false,"compliant_bact":false,"date":"2025-08-12T14:24:00Z"},"PFHPA":{"code":"PFHPA","label":"Acide perfluoroheptanoïque (PFHPA)","value":0,"unit":"µg/L","reference":null,"limit":null,"compliant_pc":false,"compliant_bact":false,"date":"2025-08-12T14:24:00Z"},"PFDODS":{"code":"PFDODS","label":"Acide perfluorododécane sulfonique (PFDoDS)","value":0,"unit":"µg/L","reference":null,"limit":null,"compliant_pc":false,"compliant_bact":false,"date":"2025-08-12T14:24:00Z"},"PFNS":{"code":"PFNS","label":"Acide perfluorononane sulfonique (PFNS)","value":0,"unit":"µg/L","reference":null,"limit":null,"compliant_pc":false,"compliant_bact":false,"date":"2025-08-12T14:24:00Z"}},"history":{"ECOLI":[{"date":"2025-06-12","value":0,"c":0},{"date":"2025-07-09","value":0,"c":1},{"date":"2025-10-20","value":4,"c":0},{"date":"2025-11-03","value":0,"c":1},{"date":"2025-12-01","value":16,"c":0},{"date":"2025-12-05","value":0,"c":1},{"date":"2025-12-11","value":0,"c":1},{"date":"2026-01-27","value":0,"c":0}],"CL2LIB":[{"date":"2025-06-12","value":0,"c":0},{"date":"2025-07-09","value":0,"c":1},{"date":"2025-10-20","value":0,"c":0},{"date":"2025-11-03","value":0,"c":1},{"date":"2025-12-01","value":0,"c":0},{"date":"2025-12-05","value":0.05,"c":1},{"date":"2025-12-11","value":0.05,"c":1},{"date":"2026-01-27","value":0.11,"c":0}],"NO3":[{"date":"2025-07-09","value":26,"c":1},{"date":"2025-12-11","value":39,"c":1},{"date":"2026-01-27","value":37,"c":0}],"PH":[{"date":"2025-06-12","value":8.1,"c":0},{"date":"2025-06-12","value":8,"c":0},{"date":"2025-07-09","value":7.7,"c":1},{"date":"2025-10-20","value":7.7,"c":0},{"date":"2025-11-03","value":7.7,"c":1},{"date":"2025-12-01","value":7.7,"c":0},{"date":"2025-12-05","value":7.7,"c":1},{"date":"2025-12-11","value":7.6,"c":1},{"date":"2026-01-27","value":7.8,"c":0}],"STRF":[{"date":"2025-06-12","value":0,"c":0},{"date":"2025-07-09","value":0,"c":1},{"date":"2025-10-20","value":0,"c":0},{"date":"2025-11-03","value":0,"c":1},{"date":"2025-12-01","value":0,"c":0},{"date":"2025-12-05","value":0,"c":1},{"date":"2025-12-11","value":0,"c":1},{"date":"2026-01-27","value":0,"c":0}],"CDT25":[{"date":"2025-06-12","value":480,"c":0},{"date":"2025-07-09","value":490,"c":1},{"date":"2025-10-20","value":450,"c":0},{"date":"2025-11-03","value":460,"c":1},{"date":"2025-12-01","value":440,"c":0},{"date":"2025-12-05","value":440,"c":1},{"date":"2025-12-11","value":430,"c":1},{"date":"2026-01-27","value":420,"c":0}],"NO2":[{"date":"2025-07-09","value":0,"c":1},{"date":"2025-12-11","value":0,"c":1},{"date":"2026-01-27","value":0,"c":0}],"NH4":[{"date":"2025-06-12","value":0,"c":0},{"date":"2025-07-09","value":0,"c":1},{"date":"2025-10-20","value":0,"c":0},{"date":"2025-12-01","value":0,"c":0},{"date":"2025-12-11","value":0,"c":1},{"date":"2026-01-27","value":0,"c":0}],"TH":[{"date":"2025-07-09","value":24.3,"c":1},{"date":"2025-12-11","value":22.3,"c":1},{"date":"2026-01-27","value":21,"c":0}],"CL2TOT":[{"date":"2025-06-12","value":0.05,"c":0},{"date":"2025-07-09","value":0.05,"c":1},{"date":"2025-10-20","value":0,"c":0},{"date":"2025-11-03","value":0.09,"c":1},{"date":"2025-12-01","value":0,"c":0},{"date":"2025-12-05","value":0.07,"c":1},{"date":"2025-12-11","value":0.1,"c":1},{"date":"2026-01-27","value":0.16,"c":0}],"TURBNFU":[{"date":"2025-06-12","value":0.5,"c":0},{"date":"2025-07-09","value":0.2,"c":1},{"date":"2025-10-20","value":0.1,"c":0},{"date":"2025-11-03","value":0.2,"c":1},{"date":"2025-12-01","value":0.1,"c":0},{"date":"2025-12-05","value":0.1,"c":1},{"date":"2025-12-11","value":0.2,"c":1},{"date":"2026-01-27","value":0.2,"c":0}],"CTF":[{"date":"2025-06-12","value":0,"c":0},{"date":"2025-07-09","value":0,"c":1},{"date":"2025-10-20","value":5,"c":0},{"date":"2025-11-03","value":0,"c":1},{"date":"2025-12-01","value":80,"c":0},{"date":"2025-12-05","value":0,"c":1},{"date":"2025-12-11","value":0,"c":1},{"date":"2026-01-27","value":0,"c":0}]},"lastSampleAllParams":[{"code":"CLDZ_MD","label":"Chloridazone méthyl desphényl","value":0.111,"unit":"µg/L","reference":null,"limit":"<=0,1 µg/L","compliant_pc":false,"compliant_bact":false,"date":"2026-02-23T11:41:00Z"},{"code":"PESTOT","label":"Total des pesticides analysés","value":0.6,"unit":"µg/L","reference":null,"limit":"<=0,5 µg/L","compliant_pc":false,"compliant_bact":false,"date":"2026-02-23T11:41:00Z"},{"code":"CLDZ_D","label":"Chloridazone desphényl","value":0.489,"unit":"µg/L","reference":null,"limit":"<=0,1 µg/L","compliant_pc":false,"compliant_bact":false,"date":"2026-02-23T11:41:00Z"}],"fetchedAt":"2026-05-29T17:15:39.673Z","coords":[4.985563,47.707551]}